<?xml version="1.0" encoding="UTF-8"?><td:AuctionData xmlns:td="http://www.treasurydirect.gov/" xmlns:xsi="http://www.w3.org/2001/XMLSchema-instance" xsi:schemaLocation="http://www.treasurydirect.gov/ https://www.treasurydirect.gov/xsd/Auction_v6_0_0.xsd">
<AuctionAnnouncement>
<SecurityTermWeekYear>30-YEAR</SecurityTermWeekYear>
<SecurityTermDayMonth>0-MONTH</SecurityTermDayMonth>
<SecurityType>BOND</SecurityType>
<CUSIP>912810TT5</CUSIP>
<AnnouncementDate>2023-08-02</AnnouncementDate>
<AuctionDate>2023-08-10</AuctionDate>
<IssueDate>2023-08-15</IssueDate>
<MaturityDate>2053-08-15</MaturityDate>
<OfferingAmount>23.000</OfferingAmount>
<CompetitiveTenderAccepted>Y</CompetitiveTenderAccepted>
<NonCompetitiveTenderAccepted>Y</NonCompetitiveTenderAccepted>
<TreasuryRetailTenderAccepted>Y</TreasuryRetailTenderAccepted>
<TypeOfAuction>SINGLE PRICE</TypeOfAuction>
<CompetitiveClosingTime>13:00</CompetitiveClosingTime>
<NonCompetitiveClosingTime>12:00</NonCompetitiveClosingTime>
<NetLongPositionReport>8050000000.0</NetLongPositionReport>
<MaxAward>8050000000</MaxAward>
<MaxSingleBid>8050000000</MaxSingleBid>
<CompetitiveBidDecimals>3</CompetitiveBidDecimals>
<CompetitiveBidIncrement>0.001</CompetitiveBidIncrement>
<AllocationPercentageDecimals>2</AllocationPercentageDecimals>
<MinBidAmount>100</MinBidAmount>
<MultiplesToBid>100</MultiplesToBid>
<MinToIssue>100</MinToIssue>
<MultiplesToIssue>100</MultiplesToIssue>
<MatureSecurityAmount>84033000000.0</MatureSecurityAmount>
<CurrentlyOutstanding/>
<SOMAIncluded>N</SOMAIncluded>
<SOMAHoldings>81174000000.0</SOMAHoldings>
<MaturingDate>2023-08-15</MaturingDate>
<FIMAIncluded>Y</FIMAIncluded>
<Series>Bonds of August 2053</Series>
<InterestRate/>
<Spread/>
<FirstInterestPaymentDate>2024-02-15</FirstInterestPaymentDate>
<StandardInterestPayment/>
<FrequencyInterestPayment>SEMI-ANNUAL</FrequencyInterestPayment>
<StrippableIndicator>Y</StrippableIndicator>
<MinStripAmount>100</MinStripAmount>
<CorpusCUSIP>912803GU1</CorpusCUSIP>
<TINTCUSIP1>912834H84</TINTCUSIP1>
<TINTCUSIP2/>
<ReOpeningIndicator>N</ReOpeningIndicator>
<OriginalIssueDate/>
<BackDated>N</BackDated>
<BackDatedDate/>
<LongShortNormalCoupon>N</LongShortNormalCoupon>
<LongShortCouponFirstIntPmt/>
<InflationIndexSecurity>N</InflationIndexSecurity>
<FloatingRate>N</FloatingRate>
<RefCPIIssueDate/>
<RefCPIDatedDate/>
<IndexRatioOnIssueDate/>
<CPIBasePeriod/>
<TIINConversionFactor/>
<AccruedInterest/>
<DatedDate>2023-08-15</DatedDate>
<AnnouncedCUSIP/>
<UnadjustedPrice/>
<UnadjustedAccruedInterest/>
<AnnouncementPDFName/>
<OriginalDatedDate/>
<AdjustedAmountCurrentlyOutstanding/>
<NLPExclusionAmount>0.0</NLPExclusionAmount>
<MaximumNonCompAward>10000000.0</MaximumNonCompAward>
<AdjustedAccruedInterest/>
<Callable>N</Callable>
<CallDate/>
</AuctionAnnouncement>
<AuctionResults>
<LongShortCouponFirstIntPmt/>
<PrimaryDealerTendered>29727000000</PrimaryDealerTendered>
<PrimaryDealerAccepted>2875537500</PrimaryDealerAccepted>
<DirectBidderTendered>8249000000</DirectBidderTendered>
<DirectBidderAccepted>4509000000</DirectBidderAccepted>
<IndirectBidderTendered>17584849000</IndirectBidderTendered>
<IndirectBidderAccepted>15570864000</IndirectBidderAccepted>
<CompetitiveTendered>55560849000</CompetitiveTendered>
<CompetitiveAccepted>22955401500</CompetitiveAccepted>
<NonCompetitiveAccepted>44608700</NonCompetitiveAccepted>
<SOMATendered>8604596200</SOMATendered>
<SOMAAccepted>8604596200</SOMAAccepted>
<FIMATendered>0</FIMATendered>
<FIMAAccepted>0</FIMAAccepted>
<TotalTendered>64210053900</TotalTendered>
<TotalAccepted>31604606400</TotalAccepted>
<BidToCoverRatio>2.42</BidToCoverRatio>
<ReleaseTime>13:01</ReleaseTime>
<AmountAcceptedBelowLowRate>5</AmountAcceptedBelowLowRate>
<HighAllocationPercentage>10.05</HighAllocationPercentage>
<LowDiscountRate/>
<HighDiscountRate/>
<MedianDiscountRate/>
<LowYield>4.050</LowYield>
<HighYield>4.189</HighYield>
<MedianYield>4.115</MedianYield>
<LowDiscountMargin/>
<HighDiscountMargin/>
<MedianDiscountMargin/>
<LowPrice/>
<HighPrice>98.912672</HighPrice>
<MedianPrice/>
<TIINConversionFactor/>
<AccruedInterest/>
<StandardInterestPayment>20.625</StandardInterestPayment>
<InterestRate>4.125</InterestRate>
<Spread/>
<OriginalCUSIP/>
<UnadjustedPrice/>
<UnadjustedAccruedInterest/>
<TreasuryRetailAccepted>25744700</TreasuryRetailAccepted>
<InvestmentRate/>
<AdjustedPrice/>
<AdjustedAccruedInterest/>
<IndexRatio/>
<FRNIndexDeterminationDate/>
<FRNIndexDeterminationRate/>
<ResultsPDFName>R_20230810_3.pdf</ResultsPDFName>
</AuctionResults>
</td:AuctionData>
